cred_manage/__init__.py
cred_manage/base_cred_container.py
cred_manage/bitwarden.py
cred_manage/flat_file.py
cred_manage-0.0.7.dist-info/LICENSE
cred_manage-0.0.7.dist-info/METADATA
cred_manage-0.0.7.dist-info/WHEEL
cred_manage-0.0.7.dist-info/top_level.txt
cred_manage-0.0.7.dist-info/RECORD
