Metadata-Version: 2.1
Name: cred-manage
Version: 0.0.7
Summary: Abstractions to read / write / delete secrets from keyrings, vaults, flat files, etc
Home-page: https://github.com/areese801/cred_manage
Author: Adam Reese
Author-email: areese801@gmail.com
License: UNKNOWN
Project-URL: Bug Tracker, https://github.com/areese801/cred_manage/issues
Platform: UNKNOWN
Classifier: Programming Language :: Python :: 3
Classifier: License :: OSI Approved :: MIT License
Classifier: Operating System :: OS Independent
Requires-Python: >=3.6
License-File: LICENSE
Requires-Dist: packaging (>=21.3)
